setup.py
jarbas_house/__init__.py
jarbas_house/settings.py
jarbas_house/util.py
jarbas_house.egg-info/PKG-INFO
jarbas_house.egg-info/SOURCES.txt
jarbas_house.egg-info/dependency_links.txt
jarbas_house.egg-info/requires.txt
jarbas_house.egg-info/top_level.txt
jarbas_house/colors/__init__.py
jarbas_house/devices/__init__.py
jarbas_house/devices/scan.py
jarbas_house/devices/ewelink/__init__.py
jarbas_house/devices/ewelink/sonoff.py
jarbas_house/devices/magic_home/__init__.py
jarbas_house/devices/magic_home/magichome.py
jarbas_house/devices/magic_home/utils.py
jarbas_house/devices/tplink/__init__.py