Metadata-Version: 1.0
Name: jarbas-house
Version: 0.1.3
Summary: tools to control my iot devices
Home-page: UNKNOWN
Author: jarbasai
Author-email: jarbasai@mailfence.com
License: MIT
Platform: UNKNOWN
